Workbook

Sheet Instructions
B2: Sales & Inventory Tracker
B3: Template for small businesses · log your sales and everything else is calculated
B5: How to use it
B6: 1. Products: enter your items (unique code, name, category, price, unit cost, opening stock and minimum stock).
B7: 2. Sales: log each sale with date, code, quantity and discount. Product, price, total, cost and margin fill in automatically.
B8: 3. Dashboard: key metrics, sales by month and by category, and reorder alerts.
B10: Editable cells
B11: Only type in cells with a yellow background. Every other cell holds a formula.
B13: Sample data
B14: The products and sales included are fictional so you can see how it works. Clear them (yellow cells only) and enter your own.
B16: Capacity
B17: Up to 200 products and 1000 sales. For more rows, copy the last formula row down.
... B20: Excel 2010 or later, Google Sheets and LibreOffice. No macros.

Sheet Dashboard
B2: Sales & Inventory Tracker
B4: Total revenue | C4: =SUM(Sales!$H$2:$H$1001) -> 2463.31
B5: Units sold | C5: =SUM(Sales!$C$2:$C$1001) -> 255
B6: Number of sales | C6: =COUNT(Sales!$A$2:$A$1001) -> 146
B7: Average ticket | C7: =IF(C6=0,0,C4/C6) -> 16.871986
B8: Gross margin | C8: =SUM(Sales!$J$2:$J$1001) -> 1310.71
B9: Margin % | C9: =IF(C4=0,0,C8/C4) -> 0.532093
B10: Products to reorder | C10: =COUNTIF(Products!$J$2:$J$201,"Reorder") -> 2
B11: Best-selling product | C11: =IFERROR(INDEX(Products!$B$2:$B$201,MATCH(MAX(Products!$H$2:$H$201),Products!$H$2:$H$201,0)),"") -> Ground coffee 500 g
B13: First month of report | C13: 46023
B15: Month | C15: Revenue | D15: Units | E15: Gross margin | G15: Category | H15: Revenue | I15: Units | J15: Gross margin
B16: =DATE(YEAR($C$13),MONTH($C$13)+0,1) -> 46023 | C16: =SUMIFS(Sales!$H$2:$H$1001,Sales!$K$2:$K$1001,$B16) -> 95.05 | D16: =SUMIFS(Sales!$C$2:$C$1001,Sales!$K$2:$K$1001,$B16) -> 11 | E16: =SUMIFS(Sales!$J$2:$J$1001,Sales!$K$2:$K$1001,$B16) -> 51.15 | G16: Coffee | H16: =IF($G16="","",SUMIFS(Sales!$H$2:$H$1001,Sales!$F$2:$F$1001,$G16)) -> 1477.6 | I16: =IF($G16="","",SUMIFS(Sales!$C$2:$C$1001,Sales!$F$2:$F$1001,$G16)) -> 110 | J16: =IF($G16="","",SUMIFS(Sales!$J$2:$J$1001,Sales!$F$2:$F$1001,$G16)) -> 750.1
B17: =DATE(YEAR($C$13),MONTH($C$13)+1,1) -> 46054 | C17: =SUMIFS(Sales!$H$2:$H$1001,Sales!$K$2:$K$1001,$B17) -> 211.91 | D17: =SUMIFS(Sales!$C$2:$C$1001,Sales!$K$2:$K$1001,$B17) -> 23 | E17: =SUMIFS(Sales!$J$2:$J$1001,Sales!$K$2:$K$1001,$B17) -> 110.31 | G17: Tea | H17: =IF($G17="","",SUMIFS(Sales!$H$2:$H$1001,Sales!$F$2:$F$1001,$G17)) -> 202.7 | I17: =IF($G17="","",SUMIFS(Sales!$C$2:$C$1001,Sales!$F$2:$F$1001,$G17)) -> 34 | J17: =IF($G17="","",SUMIFS(Sales!$J$2:$J$1001,Sales!$F$2:$F$1001,$G17)) -> 119.5
B18: =DATE(YEAR($C$13),MONTH($C$13)+2,1) -> 46082 | C18: =SUMIFS(Sales!$H$2:$H$1001,Sales!$K$2:$K$1001,$B18) -> 299.39 | D18: =SUMIFS(Sales!$C$2:$C$1001,Sales!$K$2:$K$1001,$B18) -> 32 | E18: =SUMIFS(Sales!$J$2:$J$1001,Sales!$K$2:$K$1001,$B18) -> 159.49 | G18: Accessories | H18: =IF($G18="","",SUMIFS(Sales!$H$2:$H$1001,Sales!$F$2:$F$1001,$G18)) -> 554.25 | I18: =IF($G18="","",SUMIFS(Sales!$C$2:$C$1001,Sales!$F$2:$F$1001,$G18)) -> 57 | J18: =IF($G18="","",SUMIFS(Sales!$J$2:$J$1001,Sales!$F$2:$F$1001,$G18)) -> 304.55
B19: =DATE(YEAR($C$13),MONTH($C$13)+3,1) -> 46113 | C19: =SUMIFS(Sales!$H$2:$H$1001,Sales!$K$2:$K$1001,$B19) -> 230.575 | D19: =SUMIFS(Sales!$C$2:$C$1001,Sales!$K$2:$K$1001,$B19) -> 26 | E19: =SUMIFS(Sales!$J$2:$J$1001,Sales!$K$2:$K$1001,$B19) -> 120.475 | G19: Snacks | H19: =IF($G19="","",SUMIFS(Sales!$H$2:$H$1001,Sales!$F$2:$F$1001,$G19)) -> 228.76 | I19: =IF($G19="","",SUMIFS(Sales!$C$2:$C$1001,Sales!$F$2:$F$1001,$G19)) -> 54 | J19: =IF($G19="","",SUMIFS(Sales!$J$2:$J$1001,Sales!$F$2:$F$1001,$G19)) -> 136.56
B20: =DATE(YEAR($C$13),MONTH($C$13)+4,1) -> 46143 | C20: =SUMIFS(Sales!$H$2:$H$1001,Sales!$K$2:$K$1001,$B20) -> 285.38 | D20: =SUMIFS(Sales!$C$2:$C$1001,Sales!$K$2:$K$1001,$B20) -> 24 | E20: =SUMIFS(Sales!$J$2:$J$1001,Sales!$K$2:$K$1001,$B20) -> 149.28 | H20: =IF($G20="","",SUMIFS(Sales!$H$2:$H$1001,Sales!$F$2:$F$1001,$G20)) | I20: =IF($G20="","",SUMIFS(Sales!$C$2:$C$1001,Sales!$F$2:$F$1001,$G20)) | J20: =IF($G20="","",SUMIFS(Sales!$J$2:$J$1001,Sales!$F$2:$F$1001,$G20))
B21: =DATE(YEAR($C$13),MONTH($C$13)+5,1) -> 46174 | C21: =SUMIFS(Sales!$H$2:$H$1001,Sales!$K$2:$K$1001,$B21) -> 359.5 | D21: =SUMIFS(Sales!$C$2:$C$1001,Sales!$K$2:$K$1001,$B21) -> 30 | E21: =SUMIFS(Sales!$J$2:$J$1001,Sales!$K$2:$K$1001,$B21) -> 191.1 | H21: =IF($G21="","",SUMIFS(Sales!$H$2:$H$1001,Sales!$F$2:$F$1001,$G21)) | I21: =IF($G21="","",SUMIFS(Sales!$C$2:$C$1001,Sales!$F$2:$F$1001,$G21)) | J21: =IF($G21="","",SUMIFS(Sales!$J$2:$J$1001,Sales!$F$2:$F$1001,$G21))
B22: =DATE(YEAR($C$13),MONTH($C$13)+6,1) -> 46204 | C22: =SUMIFS(Sales!$H$2:$H$1001,Sales!$K$2:$K$1001,$B22) -> 293.28 | D22: =SUMIFS(Sales!$C$2:$C$1001,Sales!$K$2:$K$1001,$B22) -> 32 | E22: =SUMIFS(Sales!$J$2:$J$1001,Sales!$K$2:$K$1001,$B22) -> 157.18 | H22: =IF($G22="","",SUMIFS(Sales!$H$2:$H$1001,Sales!$F$2:$F$1001,$G22)) | I22: =IF($G22="","",SUMIFS(Sales!$C$2:$C$1001,Sales!$F$2:$F$1001,$G22)) | J22: =IF($G22="","",SUMIFS(Sales!$J$2:$J$1001,Sales!$F$2:$F$1001,$G22))
B23: =DATE(YEAR($C$13),MONTH($C$13)+7,1) -> 46235 | C23: =SUMIFS(Sales!$H$2:$H$1001,Sales!$K$2:$K$1001,$B23) -> 353.81 | D23: =SUMIFS(Sales!$C$2:$C$1001,Sales!$K$2:$K$1001,$B23) -> 42 | E23: =SUMIFS(Sales!$J$2:$J$1001,Sales!$K$2:$K$1001,$B23) -> 192.41 | H23: =IF($G23="","",SUMIFS(Sales!$H$2:$H$1001,Sales!$F$2:$F$1001,$G23)) | I23: =IF($G23="","",SUMIFS(Sales!$C$2:$C$1001,Sales!$F$2:$F$1001,$G23)) | J23: =IF($G23="","",SUMIFS(Sales!$J$2:$J$1001,Sales!$F$2:$F$1001,$G23))
B24: =DATE(YEAR($C$13),MONTH($C$13)+8,1) -> 46266 | C24: =SUMIFS(Sales!$H$2:$H$1001,Sales!$K$2:$K$1001,$B24) -> 334.415 | D24: =SUMIFS(Sales!$C$2:$C$1001,Sales!$K$2:$K$1001,$B24) -> 35 | E24: =SUMIFS(Sales!$J$2:$J$1001,Sales!$K$2:$K$1001,$B24) -> 179.315
B25: =DATE(YEAR($C$13),MONTH($C$13)+9,1) -> 46296 | C25: =SUMIFS(Sales!$H$2:$H$1001,Sales!$K$2:$K$1001,$B25) -> 0 | D25: =SUMIFS(Sales!$C$2:$C$1001,Sales!$K$2:$K$1001,$B25) -> 0 | E25: =SUMIFS(Sales!$J$2:$J$1001,Sales!$K$2:$K$1001,$B25) -> 0 | G25: Type your categories here (same text as in Products).
B26: =DATE(YEAR($C$13),MONTH($C$13)+10,1) -> 46327 | C26: =SUMIFS(Sales!$H$2:$H$1001,Sales!$K$2:$K$1001,$B26) -> 0 | D26: =SUMIFS(Sales!$C$2:$C$1001,Sales!$K$2:$K$1001,$B26) -> 0 | E26: =SUMIFS(Sales!$J$2:$J$1001,Sales!$K$2:$K$1001,$B26) -> 0
B27: =DATE(YEAR($C$13),MONTH($C$13)+11,1) -> 46357 | C27: =SUMIFS(Sales!$H$2:$H$1001,Sales!$K$2:$K$1001,$B27) -> 0 | D27: =SUMIFS(Sales!$C$2:$C$1001,Sales!$K$2:$K$1001,$B27) -> 0 | E27: =SUMIFS(Sales!$J$2:$J$1001,Sales!$K$2:$K$1001,$B27) -> 0

Sheet Products
A1: Code | B1: Product | C1: Category | D1: Sale price | E1: Unit cost | F1: Opening stock | G1: Minimum stock | H1: Units sold | I1: Current stock | J1: Status | K1: Revenue | L1: Gross margin | M1: Margin %
A2: COF-001 | B2: Whole bean coffee 250 g | C2: Coffee | D2: 9.5 | E2: 4.5 | F2: 120 | G2: 20 | H2: =IF($A2="","",SUMIFS(Sales!$C$2:$C$1001,Sales!$B$2:$B$1001,$A2)) -> 33 | I2: =IF($A2="","",F2-H2) -> 87 | J2: =IF($A2="","",IF(I2<=G2,"Reorder","OK")) -> OK | K2: =IF($A2="","",SUMIFS(Sales!$H$2:$H$1001,Sales!$B$2:$B$1001,$A2)) -> 309.7 | L2: =IF($A2="","",SUMIFS(Sales!$J$2:$J$1001,Sales!$B$2:$B$1001,$A2)) -> 161.2 | M2: =IF($A2="","",IF(K2=0,0,L2/K2)) -> 0.52050371
A3: COF-002 | B3: Ground coffee 500 g | C3: Coffee | D3: 16 | E3: 7.8 | F3: 90 | G3: 15 | H3: =IF($A3="","",SUMIFS(Sales!$C$2:$C$1001,Sales!$B$2:$B$1001,$A3)) -> 53 | I3: =IF($A3="","",F3-H3) -> 37 | J3: =IF($A3="","",IF(I3<=G3,"Reorder","OK")) -> OK | K3: =IF($A3="","",SUMIFS(Sales!$H$2:$H$1001,Sales!$B$2:$B$1001,$A3)) -> 836.8 | L3: =IF($A3="","",SUMIFS(Sales!$J$2:$J$1001,Sales!$B$2:$B$1001,$A3)) -> 423.4 | M3: =IF($A3="","",IF(K3=0,0,L3/K3)) -> 0.50597514
A4: COF-003 | B4: Specialty coffee 250 g | C4: Coffee | D4: 14 | E4: 6.9 | F4: 60 | G4: 15 | H4: =IF($A4="","",SUMIFS(Sales!$C$2:$C$1001,Sales!$B$2:$B$1001,$A4)) -> 24 | I4: =IF($A4="","",F4-H4) -> 36 | J4: =IF($A4="","",IF(I4<=G4,"Reorder","OK")) -> OK | K4: =IF($A4="","",SUMIFS(Sales!$H$2:$H$1001,Sales!$B$2:$B$1001,$A4)) -> 331.1 | L4: =IF($A4="","",SUMIFS(Sales!$J$2:$J$1001,Sales!$B$2:$B$1001,$A4)) -> 165.5 | M4: =IF($A4="","",IF(K4=0,0,L4/K4)) -> 0.49984899
A5: TEA-001 | B5: Green tea 50 g | C5: Tea | D5: 5.5 | E5: 2.2 | F5: 70 | G5: 10 | H5: =IF($A5="","",SUMIFS(Sales!$C$2:$C$1001,Sales!$B$2:$B$1001,$A5)) -> 13 | I5: =IF($A5="","",F5-H5) -> 57 | J5: =IF($A5="","",IF(I5<=G5,"Reorder","OK")) -> OK | K5: =IF($A5="","",SUMIFS(Sales!$H$2:$H$1001,Sales!$B$2:$B$1001,$A5)) -> 68.475 | L5: =IF($A5="","",SUMIFS(Sales!$J$2:$J$1001,Sales!$B$2:$B$1001,$A5)) -> 39.875 | M5: =IF($A5="","",IF(K5=0,0,L5/K5)) -> 0.58232932
A6: TEA-002 | B6: Chai tea 50 g | C6: Tea | D6: 6.5 | E6: 2.6 | F6: 30 | G6: 10 | H6: =IF($A6="","",SUMIFS(Sales!$C$2:$C$1001,Sales!$B$2:$B$1001,$A6)) -> 21 | I6: =IF($A6="","",F6-H6) -> 9 | J6: =IF($A6="","",IF(I6<=G6,"Reorder","OK")) -> Reorder | K6: =IF($A6="","",SUMIFS(Sales!$H$2:$H$1001,Sales!$B$2:$B$1001,$A6)) -> 134.225 | L6: =IF($A6="","",SUMIFS(Sales!$J$2:$J$1001,Sales!$B$2:$B$1001,$A6)) -> 79.625 | M6: =IF($A6="","",IF(K6=0,0,L6/K6)) -> 0.59322034
A7: ACC-001 | B7: Ceramic mug | C7: Accessories | D7: 10 | E7: 4 | F7: 50 | G7: 8 | H7: =IF($A7="","",SUMIFS(Sales!$C$2:$C$1001,Sales!$B$2:$B$1001,$A7)) -> 13 | I7: =IF($A7="","",F7-H7) -> 37 | J7: =IF($A7="","",IF(I7<=G7,"Reorder","OK")) -> OK | K7: =IF($A7="","",SUMIFS(Sales!$H$2:$H$1001,Sales!$B$2:$B$1001,$A7)) -> 128 | L7: =IF($A7="","",SUMIFS(Sales!$J$2:$J$1001,Sales!$B$2:$B$1001,$A7)) -> 76 | M7: =IF($A7="","",IF(K7=0,0,L7/K7)) -> 0.59375
A8: ACC-002 | B8: Steel tumbler 500 ml | C8: Accessories | D8: 19 | E8: 9 | F8: 35 | G8: 6 | H8: =IF($A8="","",SUMIFS(Sales!$C$2:$C$1001,Sales!$B$2:$B$1001,$A8)) -> 5 | I8: =IF($A8="","",F8-H8) -> 30 | J8: =IF($A8="","",IF(I8<=G8,"Reorder","OK")) -> OK | K8: =IF($A8="","",SUMIFS(Sales!$H$2:$H$1001,Sales!$B$2:$B$1001,$A8)) -> 95 | L8: =IF($A8="","",SUMIFS(Sales!$J$2:$J$1001,Sales!$B$2:$B$1001,$A8)) -> 50 | M8: =IF($A8="","",IF(K8=0,0,L8/K8)) -> 0.52631579
A9: ACC-003 | B9: Paper filters (100 pcs) | C9: Accessories | D9: 4.5 | E9: 1.7 | F9: 80 | G9: 15 | H9: =IF($A9="","",SUMIFS(Sales!$C$2:$C$1001,Sales!$B$2:$B$1001,$A9)) -> 31 | I9: =IF($A9="","",F9-H9) -> 49 | J9: =IF($A9="","",IF(I9<=G9,"Reorder","OK")) -> OK | K9: =IF($A9="","",SUMIFS(Sales!$H$2:$H$1001,Sales!$B$2:$B$1001,$A9)) -> 135 | L9: =IF($A9="","",SUMIFS(Sales!$J$2:$J$1001,Sales!$B$2:$B$1001,$A9)) -> 82.3 | M9: =IF($A9="","",IF(K9=0,0,L9/K9)) -> 0.60962963
A10: ACC-004 | B10: French press 600 ml | C10: Accessories | D10: 25 | E10: 12.5 | F10: 12 | G10: 5 | H10: =IF($A10="","",SUMIFS(Sales!$C$2:$C$1001,Sales!$B$2:$B$1001,$A10)) -> 8 | I10: =IF($A10="","",F10-H10) -> 4 | J10: =IF($A10="","",IF(I10<=G10,"Reorder","OK")) -> Reorder | K10: =IF($A10="","",SUMIFS(Sales!$H$2:$H$1001,Sales!$B$2:$B$1001,$A10)) -> 196.25 | L10: =IF($A10="","",SUMIFS(Sales!$J$2:$J$1001,Sales!$B$2:$B$1001,$A10)) -> 96.25 | M10: =IF($A10="","",IF(K10=0,0,L10/K10)) -> 0.49044586
A11: SNK-001 | B11: Oat cookies (6 pcs) | C11: Snacks | D11: 3.8 | E11: 1.4 | F11: 100 | G11: 20 | H11: =IF($A11="","",SUMIFS(Sales!$C$2:$C$1001,Sales!$B$2:$B$1001,$A11)) -> 28 | I11: =IF($A11="","",F11-H11) -> 72 | J11: =IF($A11="","",IF(I11<=G11,"Reorder","OK")) -> OK | K11: =IF($A11="","",SUMIFS(Sales!$H$2:$H$1001,Sales!$B$2:$B$1001,$A11)) -> 102.03 | L11: =IF($A11="","",SUMIFS(Sales!$J$2:$J$1001,Sales!$B$2:$B$1001,$A11)) -> 62.83 | M11: =IF($A11="","",IF(K11=0,0,L11/K11)) -> 0.61579927
A12: SNK-002 | B12: Dark chocolate bar 70% | C12: Snacks | D12: 3.2 | E12: 1.3 | F12: 90 | G12: 20 | H12: =IF($A12="","",SUMIFS(Sales!$C$2:$C$1001,Sales!$B$2:$B$1001,$A12)) -> 14 | I12: =IF($A12="","",F12-H12) -> 76 | J12: =IF($A12="","",IF(I12<=G12,"Reorder","OK")) -> OK | K12: =IF($A12="","",SUMIFS(Sales!$H$2:$H$1001,Sales!$B$2:$B$1001,$A12)) -> 44.48 | L12: =IF($A12="","",SUMIFS(Sales!$J$2:$J$1001,Sales!$B$2:$B$1001,$A12)) -> 26.28 | M12: =IF($A12="","",IF(K12=0,0,L12/K12)) -> 0.59082734
A13: SNK-003 | B13: Granola 300 g | C13: Snacks | D13: 7 | E13: 2.9 | F13: 40 | G13: 10 | H13: =IF($A13="","",SUMIFS(Sales!$C$2:$C$1001,Sales!$B$2:$B$1001,$A13)) -> 12 | I13: =IF($A13="","",F13-H13) -> 28 | J13: =IF($A13="","",IF(I13<=G13,"Reorder","OK")) -> OK | K13: =IF($A13="","",SUMIFS(Sales!$H$2:$H$1001,Sales!$B$2:$B$1001,$A13)) -> 82.25 | L13: =IF($A13="","",SUMIFS(Sales!$J$2:$J$1001,Sales!$B$2:$B$1001,$A13)) -> 47.45 | M13: =IF($A13="","",IF(K13=0,0,L13/K13)) -> 0.5768997
H14: =IF($A14="","",SUMIFS(Sales!$C$2:$C$1001,Sales!$B$2:$B$1001,$A14)) | I14: =IF($A14="","",F14-H14) | J14: =IF($A14="","",IF(I14<=G14,"Reorder","OK")) | K14: =IF($A14="","",SUMIFS(Sales!$H$2:$H$1001,Sales!$B$2:$B$1001,$A14)) | L14: =IF($A14="","",SUMIFS(Sales!$J$2:$J$1001,Sales!$B$2:$B$1001,$A14)) | M14: =IF($A14="","",IF(K14=0,0,L14/K14))
H15: =IF($A15="","",SUMIFS(Sales!$C$2:$C$1001,Sales!$B$2:$B$1001,$A15)) | I15: =IF($A15="","",F15-H15) | J15: =IF($A15="","",IF(I15<=G15,"Reorder","OK")) | K15: =IF($A15="","",SUMIFS(Sales!$H$2:$H$1001,Sales!$B$2:$B$1001,$A15)) | L15: =IF($A15="","",SUMIFS(Sales!$J$2:$J$1001,Sales!$B$2:$B$1001,$A15)) | M15: =IF($A15="","",IF(K15=0,0,L15/K15))
H16: =IF($A16="","",SUMIFS(Sales!$C$2:$C$1001,Sales!$B$2:$B$1001,$A16)) | I16: =IF($A16="","",F16-H16) | J16: =IF($A16="","",IF(I16<=G16,"Reorder","OK")) | K16: =IF($A16="","",SUMIFS(Sales!$H$2:$H$1001,Sales!$B$2:$B$1001,$A16)) | L16: =IF($A16="","",SUMIFS(Sales!$J$2:$J$1001,Sales!$B$2:$B$1001,$A16)) | M16: =IF($A16="","",IF(K16=0,0,L16/K16))
H17: =IF($A17="","",SUMIFS(Sales!$C$2:$C$1001,Sales!$B$2:$B$1001,$A17)) | I17: =IF($A17="","",F17-H17) | J17: =IF($A17="","",IF(I17<=G17,"Reorder","OK")) | K17: =IF($A17="","",SUMIFS(Sales!$H$2:$H$1001,Sales!$B$2:$B$1001,$A17)) | L17: =IF($A17="","",SUMIFS(Sales!$J$2:$J$1001,Sales!$B$2:$B$1001,$A17)) | M17: =IF($A17="","",IF(K17=0,0,L17/K17))
H18: =IF($A18="","",SUMIFS(Sales!$C$2:$C$1001,Sales!$B$2:$B$1001,$A18)) | I18: =IF($A18="","",F18-H18) | J18: =IF($A18="","",IF(I18<=G18,"Reorder","OK")) | K18: =IF($A18="","",SUMIFS(Sales!$H$2:$H$1001,Sales!$B$2:$B$1001,$A18)) | L18: =IF($A18="","",SUMIFS(Sales!$J$2:$J$1001,Sales!$B$2:$B$1001,$A18)) | M18: =IF($A18="","",IF(K18=0,0,L18/K18))
H19: =IF($A19="","",SUMIFS(Sales!$C$2:$C$1001,Sales!$B$2:$B$1001,$A19)) | I19: =IF($A19="","",F19-H19) | J19: =IF($A19="","",IF(I19<=G19,"Reorder","OK")) | K19: =IF($A19="","",SUMIFS(Sales!$H$2:$H$1001,Sales!$B$2:$B$1001,$A19)) | L19: =IF($A19="","",SUMIFS(Sales!$J$2:$J$1001,Sales!$B$2:$B$1001,$A19)) | M19: =IF($A19="","",IF(K19=0,0,L19/K19))
H20: =IF($A20="","",SUMIFS(Sales!$C$2:$C$1001,Sales!$B$2:$B$1001,$A20)) | I20: =IF($A20="","",F20-H20) | J20: =IF($A20="","",IF(I20<=G20,"Reorder","OK")) | K20: =IF($A20="","",SUMIFS(Sales!$H$2:$H$1001,Sales!$B$2:$B$1001,$A20)) | L20: =IF($A20="","",SUMIFS(Sales!$J$2:$J$1001,Sales!$B$2:$B$1001,$A20)) | M20: =IF($A20="","",IF(K20=0,0,L20/K20))
H21: =IF($A21="","",SUMIFS(Sales!$C$2:$C$1001,Sales!$B$2:$B$1001,$A21)) | I21: =IF($A21="","",F21-H21) | J21: =IF($A21="","",IF(I21<=G21,"Reorder","OK")) | K21: =IF($A21="","",SUMIFS(Sales!$H$2:$H$1001,Sales!$B$2:$B$1001,$A21)) | L21: =IF($A21="","",SUMIFS(Sales!$J$2:$J$1001,Sales!$B$2:$B$1001,$A21)) | M21: =IF($A21="","",IF(K21=0,0,L21/K21))
H22: =IF($A22="","",SUMIFS(Sales!$C$2:$C$1001,Sales!$B$2:$B$1001,$A22)) | I22: =IF($A22="","",F22-H22) | J22: =IF($A22="","",IF(I22<=G22,"Reorder","OK")) | K22: =IF($A22="","",SUMIFS(Sales!$H$2:$H$1001,Sales!$B$2:$B$1001,$A22)) | L22: =IF($A22="","",SUMIFS(Sales!$J$2:$J$1001,Sales!$B$2:$B$1001,$A22)) | M22: =IF($A22="","",IF(K22=0,0,L22/K22))
H23: =IF($A23="","",SUMIFS(Sales!$C$2:$C$1001,Sales!$B$2:$B$1001,$A23)) | I23: =IF($A23="","",F23-H23) | J23: =IF($A23="","",IF(I23<=G23,"Reorder","OK")) | K23: =IF($A23="","",SUMIFS(Sales!$H$2:$H$1001,Sales!$B$2:$B$1001,$A23)) | L23: =IF($A23="","",SUMIFS(Sales!$J$2:$J$1001,Sales!$B$2:$B$1001,$A23)) | M23: =IF($A23="","",IF(K23=0,0,L23/K23))
H24: =IF($A24="","",SUMIFS(Sales!$C$2:$C$1001,Sales!$B$2:$B$1001,$A24)) | I24: =IF($A24="","",F24-H24) | J24: =IF($A24="","",IF(I24<=G24,"Reorder","OK")) | K24: =IF($A24="","",SUMIFS(Sales!$H$2:$H$1001,Sales!$B$2:$B$1001,$A24)) | L24: =IF($A24="","",SUMIFS(Sales!$J$2:$J$1001,Sales!$B$2:$B$1001,$A24)) | M24: =IF($A24="","",IF(K24=0,0,L24/K24))
H25: =IF($A25="","",SUMIFS(Sales!$C$2:$C$1001,Sales!$B$2:$B$1001,$A25)) | I25: =IF($A25="","",F25-H25) | J25: =IF($A25="","",IF(I25<=G25,"Reorder","OK")) | K25: =IF($A25="","",SUMIFS(Sales!$H$2:$H$1001,Sales!$B$2:$B$1001,$A25)) | L25: =IF($A25="","",SUMIFS(Sales!$J$2:$J$1001,Sales!$B$2:$B$1001,$A25)) | M25: =IF($A25="","",IF(K25=0,0,L25/K25))
... H201: =IF($A201="","",SUMIFS(Sales!$C$2:$C$1001,Sales!$B$2:$B$1001,$A201)) | I201: =IF($A201="","",F201-H201) | J201: =IF($A201="","",IF(I201<=G201,"Reorder","OK")) | K201: =IF($A201="","",SUMIFS(Sales!$H$2:$H$1001,Sales!$B$2:$B$1001,$A201)) | L201: =IF($A201="","",SUMIFS(Sales!$J$2:$J$1001,Sales!$B$2:$B$1001,$A201)) | M201: =IF($A201="","",IF(K201=0,0,L201/K201))

Sheet Sales
A1: Date | B1: Code | C1: Quantity | D1: Discount | E1: Product | F1: Category | G1: Unit price | H1: Total | I1: Cost | J1: Margin | K1: Month
A2: 46026 | B2: COF-002 | C2: 1 | D2: 0.1 | E2: =IF($B2="","",IFERROR(INDEX(Products!$B$2:$B$201,MATCH($B2,Products!$A$2:$A$201,0)),"Unknown code")) -> Ground coffee 500 g | F2: =IF($B2="","",IFERROR(INDEX(Products!$C$2:$C$201,MATCH($B2,Products!$A$2:$A$201,0)),"")) -> Coffee | G2: =IF($B2="","",IFERROR(INDEX(Products!$D$2:$D$201,MATCH($B2,Products!$A$2:$A$201,0)),0)) -> 16 | H2: =IF($B2="","",C2*G2*(1-D2)) -> 14.4 | I2: =IF($B2="","",C2*IFERROR(INDEX(Products!$E$2:$E$201,MATCH($B2,Products!$A$2:$A$201,0)),0)) -> 7.8 | J2: =IF($B2="","",H2-I2) -> 6.6 | K2: =IF($A2="","",DATE(YEAR($A2),MONTH($A2),1)) -> 46023
A3: 46033 | B3: ACC-001 | C3: 1 | D3: 0.05 | E3: =IF($B3="","",IFERROR(INDEX(Products!$B$2:$B$201,MATCH($B3,Products!$A$2:$A$201,0)),"Unknown code")) -> Ceramic mug | F3: =IF($B3="","",IFERROR(INDEX(Products!$C$2:$C$201,MATCH($B3,Products!$A$2:$A$201,0)),"")) -> Accessories | G3: =IF($B3="","",IFERROR(INDEX(Products!$D$2:$D$201,MATCH($B3,Products!$A$2:$A$201,0)),0)) -> 10 | H3: =IF($B3="","",C3*G3*(1-D3)) -> 9.5 | I3: =IF($B3="","",C3*IFERROR(INDEX(Products!$E$2:$E$201,MATCH($B3,Products!$A$2:$A$201,0)),0)) -> 4 | J3: =IF($B3="","",H3-I3) -> 5.5 | K3: =IF($A3="","",DATE(YEAR($A3),MONTH($A3),1)) -> 46023
A4: 46035 | B4: COF-002 | C4: 2 | D4: 0 | E4: =IF($B4="","",IFERROR(INDEX(Products!$B$2:$B$201,MATCH($B4,Products!$A$2:$A$201,0)),"Unknown code")) -> Ground coffee 500 g | F4: =IF($B4="","",IFERROR(INDEX(Products!$C$2:$C$201,MATCH($B4,Products!$A$2:$A$201,0)),"")) -> Coffee | G4: =IF($B4="","",IFERROR(INDEX(Products!$D$2:$D$201,MATCH($B4,Products!$A$2:$A$201,0)),0)) -> 16 | H4: =IF($B4="","",C4*G4*(1-D4)) -> 32 | I4: =IF($B4="","",C4*IFERROR(INDEX(Products!$E$2:$E$201,MATCH($B4,Products!$A$2:$A$201,0)),0)) -> 15.6 | J4: =IF($B4="","",H4-I4) -> 16.4 | K4: =IF($A4="","",DATE(YEAR($A4),MONTH($A4),1)) -> 46023
A5: 46035 | B5: SNK-001 | C5: 1 | D5: 0 | E5: =IF($B5="","",IFERROR(INDEX(Products!$B$2:$B$201,MATCH($B5,Products!$A$2:$A$201,0)),"Unknown code")) -> Oat cookies (6 pcs) | F5: =IF($B5="","",IFERROR(INDEX(Products!$C$2:$C$201,MATCH($B5,Products!$A$2:$A$201,0)),"")) -> Snacks | G5: =IF($B5="","",IFERROR(INDEX(Products!$D$2:$D$201,MATCH($B5,Products!$A$2:$A$201,0)),0)) -> 3.8 | H5: =IF($B5="","",C5*G5*(1-D5)) -> 3.8 | I5: =IF($B5="","",C5*IFERROR(INDEX(Products!$E$2:$E$201,MATCH($B5,Products!$A$2:$A$201,0)),0)) -> 1.4 | J5: =IF($B5="","",H5-I5) -> 2.4 | K5: =IF($A5="","",DATE(YEAR($A5),MONTH($A5),1)) -> 46023
A6: 46038 | B6: COF-003 | C6: 1 | D6: 0 | E6: =IF($B6="","",IFERROR(INDEX(Products!$B$2:$B$201,MATCH($B6,Products!$A$2:$A$201,0)),"Unknown code")) -> Specialty coffee 250 g | F6: =IF($B6="","",IFERROR(INDEX(Products!$C$2:$C$201,MATCH($B6,Products!$A$2:$A$201,0)),"")) -> Coffee | G6: =IF($B6="","",IFERROR(INDEX(Products!$D$2:$D$201,MATCH($B6,Products!$A$2:$A$201,0)),0)) -> 14 | H6: =IF($B6="","",C6*G6*(1-D6)) -> 14 | I6: =IF($B6="","",C6*IFERROR(INDEX(Products!$E$2:$E$201,MATCH($B6,Products!$A$2:$A$201,0)),0)) -> 6.9 | J6: =IF($B6="","",H6-I6) -> 7.1 | K6: =IF($A6="","",DATE(YEAR($A6),MONTH($A6),1)) -> 46023
A7: 46044 | B7: ACC-003 | C7: 1 | D7: 0.1 | E7: =IF($B7="","",IFERROR(INDEX(Products!$B$2:$B$201,MATCH($B7,Products!$A$2:$A$201,0)),"Unknown code")) -> Paper filters (100 pcs) | F7: =IF($B7="","",IFERROR(INDEX(Products!$C$2:$C$201,MATCH($B7,Products!$A$2:$A$201,0)),"")) -> Accessories | G7: =IF($B7="","",IFERROR(INDEX(Products!$D$2:$D$201,MATCH($B7,Products!$A$2:$A$201,0)),0)) -> 4.5 | H7: =IF($B7="","",C7*G7*(1-D7)) -> 4.05 | I7: =IF($B7="","",C7*IFERROR(INDEX(Products!$E$2:$E$201,MATCH($B7,Products!$A$2:$A$201,0)),0)) -> 1.7 | J7: =IF($B7="","",H7-I7) -> 2.35 | K7: =IF($A7="","",DATE(YEAR($A7),MONTH($A7),1)) -> 46023
A8: 46052 | B8: ACC-003 | C8: 3 | D8: 0 | E8: =IF($B8="","",IFERROR(INDEX(Products!$B$2:$B$201,MATCH($B8,Products!$A$2:$A$201,0)),"Unknown code")) -> Paper filters (100 pcs) | F8: =IF($B8="","",IFERROR(INDEX(Products!$C$2:$C$201,MATCH($B8,Products!$A$2:$A$201,0)),"")) -> Accessories | G8: =IF($B8="","",IFERROR(INDEX(Products!$D$2:$D$201,MATCH($B8,Products!$A$2:$A$201,0)),0)) -> 4.5 | H8: =IF($B8="","",C8*G8*(1-D8)) -> 13.5 | I8: =IF($B8="","",C8*IFERROR(INDEX(Products!$E$2:$E$201,MATCH($B8,Products!$A$2:$A$201,0)),0)) -> 5.1 | J8: =IF($B8="","",H8-I8) -> 8.4 | K8: =IF($A8="","",DATE(YEAR($A8),MONTH($A8),1)) -> 46023
A9: 46053 | B9: SNK-001 | C9: 1 | D9: 0 | E9: =IF($B9="","",IFERROR(INDEX(Products!$B$2:$B$201,MATCH($B9,Products!$A$2:$A$201,0)),"Unknown code")) -> Oat cookies (6 pcs) | F9: =IF($B9="","",IFERROR(INDEX(Products!$C$2:$C$201,MATCH($B9,Products!$A$2:$A$201,0)),"")) -> Snacks | G9: =IF($B9="","",IFERROR(INDEX(Products!$D$2:$D$201,MATCH($B9,Products!$A$2:$A$201,0)),0)) -> 3.8 | H9: =IF($B9="","",C9*G9*(1-D9)) -> 3.8 | I9: =IF($B9="","",C9*IFERROR(INDEX(Products!$E$2:$E$201,MATCH($B9,Products!$A$2:$A$201,0)),0)) -> 1.4 | J9: =IF($B9="","",H9-I9) -> 2.4 | K9: =IF($A9="","",DATE(YEAR($A9),MONTH($A9),1)) -> 46023
A10: 46054 | B10: COF-003 | C10: 3 | D10: 0 | E10: =IF($B10="","",IFERROR(INDEX(Products!$B$2:$B$201,MATCH($B10,Products!$A$2:$A$201,0)),"Unknown code")) -> Specialty coffee 250 g | F10: =IF($B10="","",IFERROR(INDEX(Products!$C$2:$C$201,MATCH($B10,Products!$A$2:$A$201,0)),"")) -> Coffee | G10: =IF($B10="","",IFERROR(INDEX(Products!$D$2:$D$201,MATCH($B10,Products!$A$2:$A$201,0)),0)) -> 14 | H10: =IF($B10="","",C10*G10*(1-D10)) -> 42 | I10: =IF($B10="","",C10*IFERROR(INDEX(Products!$E$2:$E$201,MATCH($B10,Products!$A$2:$A$201,0)),0)) -> 20.7 | J10: =IF($B10="","",H10-I10) -> 21.3 | K10: =IF($A10="","",DATE(YEAR($A10),MONTH($A10),1)) -> 46054
A11: 46054 | B11: COF-002 | C11: 1 | D11: 0 | E11: =IF($B11="","",IFERROR(INDEX(Products!$B$2:$B$201,MATCH($B11,Products!$A$2:$A$201,0)),"Unknown code")) -> Ground coffee 500 g | F11: =IF($B11="","",IFERROR(INDEX(Products!$C$2:$C$201,MATCH($B11,Products!$A$2:$A$201,0)),"")) -> Coffee | G11: =IF($B11="","",IFERROR(INDEX(Products!$D$2:$D$201,MATCH($B11,Products!$A$2:$A$201,0)),0)) -> 16 | H11: =IF($B11="","",C11*G11*(1-D11)) -> 16 | I11: =IF($B11="","",C11*IFERROR(INDEX(Products!$E$2:$E$201,MATCH($B11,Products!$A$2:$A$201,0)),0)) -> 7.8 | J11: =IF($B11="","",H11-I11) -> 8.2 | K11: =IF($A11="","",DATE(YEAR($A11),MONTH($A11),1)) -> 46054
A12: 46058 | B12: COF-002 | C12: 2 | D12: 0 | E12: =IF($B12="","",IFERROR(INDEX(Products!$B$2:$B$201,MATCH($B12,Products!$A$2:$A$201,0)),"Unknown code")) -> Ground coffee 500 g | F12: =IF($B12="","",IFERROR(INDEX(Products!$C$2:$C$201,MATCH($B12,Products!$A$2:$A$201,0)),"")) -> Coffee | G12: =IF($B12="","",IFERROR(INDEX(Products!$D$2:$D$201,MATCH($B12,Products!$A$2:$A$201,0)),0)) -> 16 | H12: =IF($B12="","",C12*G12*(1-D12)) -> 32 | I12: =IF($B12="","",C12*IFERROR(INDEX(Products!$E$2:$E$201,MATCH($B12,Products!$A$2:$A$201,0)),0)) -> 15.6 | J12: =IF($B12="","",H12-I12) -> 16.4 | K12: =IF($A12="","",DATE(YEAR($A12),MONTH($A12),1)) -> 46054
A13: 46060 | B13: SNK-002 | C13: 1 | D13: 0 | E13: =IF($B13="","",IFERROR(INDEX(Products!$B$2:$B$201,MATCH($B13,Products!$A$2:$A$201,0)),"Unknown code")) -> Dark chocolate bar 70% | F13: =IF($B13="","",IFERROR(INDEX(Products!$C$2:$C$201,MATCH($B13,Products!$A$2:$A$201,0)),"")) -> Snacks | G13: =IF($B13="","",IFERROR(INDEX(Products!$D$2:$D$201,MATCH($B13,Products!$A$2:$A$201,0)),0)) -> 3.2 | H13: =IF($B13="","",C13*G13*(1-D13)) -> 3.2 | I13: =IF($B13="","",C13*IFERROR(INDEX(Products!$E$2:$E$201,MATCH($B13,Products!$A$2:$A$201,0)),0)) -> 1.3 | J13: =IF($B13="","",H13-I13) -> 1.9 | K13: =IF($A13="","",DATE(YEAR($A13),MONTH($A13),1)) -> 46054
... A147: 46292 | B147: TEA-002 | C147: 2 | D147: 0 | E147: =IF($B147="","",IFERROR(INDEX(Products!$B$2:$B$201,MATCH($B147,Products!$A$2:$A$201,0)),"Unknown code")) -> Chai tea 50 g | F147: =IF($B147="","",IFERROR(INDEX(Products!$C$2:$C$201,MATCH($B147,Products!$A$2:$A$201,0)),"")) -> Tea | G147: =IF($B147="","",IFERROR(INDEX(Products!$D$2:$D$201,MATCH($B147,Products!$A$2:$A$201,0)),0)) -> 6.5 | H147: =IF($B147="","",C147*G147*(1-D147)) -> 13 | I147: =IF($B147="","",C147*IFERROR(INDEX(Products!$E$2:$E$201,MATCH($B147,Products!$A$2:$A$201,0)),0)) -> 5.2 | J147: =IF($B147="","",H147-I147) -> 7.8 | K147: =IF($A147="","",DATE(YEAR($A147),MONTH($A147),1)) -> 46266
E148: =IF($B148="","",IFERROR(INDEX(Products!$B$2:$B$201,MATCH($B148,Products!$A$2:$A$201,0)),"Unknown code")) | F148: =IF($B148="","",IFERROR(INDEX(Products!$C$2:$C$201,MATCH($B148,Products!$A$2:$A$201,0)),"")) | G148: =IF($B148="","",IFERROR(INDEX(Products!$D$2:$D$201,MATCH($B148,Products!$A$2:$A$201,0)),0)) | H148: =IF($B148="","",C148*G148*(1-D148)) | I148: =IF($B148="","",C148*IFERROR(INDEX(Products!$E$2:$E$201,MATCH($B148,Products!$A$2:$A$201,0)),0)) | J148: =IF($B148="","",H148-I148) | K148: =IF($A148="","",DATE(YEAR($A148),MONTH($A148),1))
E149: =IF($B149="","",IFERROR(INDEX(Products!$B$2:$B$201,MATCH($B149,Products!$A$2:$A$201,0)),"Unknown code")) | F149: =IF($B149="","",IFERROR(INDEX(Products!$C$2:$C$201,MATCH($B149,Products!$A$2:$A$201,0)),"")) | G149: =IF($B149="","",IFERROR(INDEX(Products!$D$2:$D$201,MATCH($B149,Products!$A$2:$A$201,0)),0)) | H149: =IF($B149="","",C149*G149*(1-D149)) | I149: =IF($B149="","",C149*IFERROR(INDEX(Products!$E$2:$E$201,MATCH($B149,Products!$A$2:$A$201,0)),0)) | J149: =IF($B149="","",H149-I149) | K149: =IF($A149="","",DATE(YEAR($A149),MONTH($A149),1))
E150: =IF($B150="","",IFERROR(INDEX(Products!$B$2:$B$201,MATCH($B150,Products!$A$2:$A$201,0)),"Unknown code")) | F150: =IF($B150="","",IFERROR(INDEX(Products!$C$2:$C$201,MATCH($B150,Products!$A$2:$A$201,0)),"")) | G150: =IF($B150="","",IFERROR(INDEX(Products!$D$2:$D$201,MATCH($B150,Products!$A$2:$A$201,0)),0)) | H150: =IF($B150="","",C150*G150*(1-D150)) | I150: =IF($B150="","",C150*IFERROR(INDEX(Products!$E$2:$E$201,MATCH($B150,Products!$A$2:$A$201,0)),0)) | J150: =IF($B150="","",H150-I150) | K150: =IF($A150="","",DATE(YEAR($A150),MONTH($A150),1))
E151: =IF($B151="","",IFERROR(INDEX(Products!$B$2:$B$201,MATCH($B151,Products!$A$2:$A$201,0)),"Unknown code")) | F151: =IF($B151="","",IFERROR(INDEX(Products!$C$2:$C$201,MATCH($B151,Products!$A$2:$A$201,0)),"")) | G151: =IF($B151="","",IFERROR(INDEX(Products!$D$2:$D$201,MATCH($B151,Products!$A$2:$A$201,0)),0)) | H151: =IF($B151="","",C151*G151*(1-D151)) | I151: =IF($B151="","",C151*IFERROR(INDEX(Products!$E$2:$E$201,MATCH($B151,Products!$A$2:$A$201,0)),0)) | J151: =IF($B151="","",H151-I151) | K151: =IF($A151="","",DATE(YEAR($A151),MONTH($A151),1))
E152: =IF($B152="","",IFERROR(INDEX(Products!$B$2:$B$201,MATCH($B152,Products!$A$2:$A$201,0)),"Unknown code")) | F152: =IF($B152="","",IFERROR(INDEX(Products!$C$2:$C$201,MATCH($B152,Products!$A$2:$A$201,0)),"")) | G152: =IF($B152="","",IFERROR(INDEX(Products!$D$2:$D$201,MATCH($B152,Products!$A$2:$A$201,0)),0)) | H152: =IF($B152="","",C152*G152*(1-D152)) | I152: =IF($B152="","",C152*IFERROR(INDEX(Products!$E$2:$E$201,MATCH($B152,Products!$A$2:$A$201,0)),0)) | J152: =IF($B152="","",H152-I152) | K152: =IF($A152="","",DATE(YEAR($A152),MONTH($A152),1))
E153: =IF($B153="","",IFERROR(INDEX(Products!$B$2:$B$201,MATCH($B153,Products!$A$2:$A$201,0)),"Unknown code")) | F153: =IF($B153="","",IFERROR(INDEX(Products!$C$2:$C$201,MATCH($B153,Products!$A$2:$A$201,0)),"")) | G153: =IF($B153="","",IFERROR(INDEX(Products!$D$2:$D$201,MATCH($B153,Products!$A$2:$A$201,0)),0)) | H153: =IF($B153="","",C153*G153*(1-D153)) | I153: =IF($B153="","",C153*IFERROR(INDEX(Products!$E$2:$E$201,MATCH($B153,Products!$A$2:$A$201,0)),0)) | J153: =IF($B153="","",H153-I153) | K153: =IF($A153="","",DATE(YEAR($A153),MONTH($A153),1))
E154: =IF($B154="","",IFERROR(INDEX(Products!$B$2:$B$201,MATCH($B154,Products!$A$2:$A$201,0)),"Unknown code")) | F154: =IF($B154="","",IFERROR(INDEX(Products!$C$2:$C$201,MATCH($B154,Products!$A$2:$A$201,0)),"")) | G154: =IF($B154="","",IFERROR(INDEX(Products!$D$2:$D$201,MATCH($B154,Products!$A$2:$A$201,0)),0)) | H154: =IF($B154="","",C154*G154*(1-D154)) | I154: =IF($B154="","",C154*IFERROR(INDEX(Products!$E$2:$E$201,MATCH($B154,Products!$A$2:$A$201,0)),0)) | J154: =IF($B154="","",H154-I154) | K154: =IF($A154="","",DATE(YEAR($A154),MONTH($A154),1))
E155: =IF($B155="","",IFERROR(INDEX(Products!$B$2:$B$201,MATCH($B155,Products!$A$2:$A$201,0)),"Unknown code")) | F155: =IF($B155="","",IFERROR(INDEX(Products!$C$2:$C$201,MATCH($B155,Products!$A$2:$A$201,0)),"")) | G155: =IF($B155="","",IFERROR(INDEX(Products!$D$2:$D$201,MATCH($B155,Products!$A$2:$A$201,0)),0)) | H155: =IF($B155="","",C155*G155*(1-D155)) | I155: =IF($B155="","",C155*IFERROR(INDEX(Products!$E$2:$E$201,MATCH($B155,Products!$A$2:$A$201,0)),0)) | J155: =IF($B155="","",H155-I155) | K155: =IF($A155="","",DATE(YEAR($A155),MONTH($A155),1))
E156: =IF($B156="","",IFERROR(INDEX(Products!$B$2:$B$201,MATCH($B156,Products!$A$2:$A$201,0)),"Unknown code")) | F156: =IF($B156="","",IFERROR(INDEX(Products!$C$2:$C$201,MATCH($B156,Products!$A$2:$A$201,0)),"")) | G156: =IF($B156="","",IFERROR(INDEX(Products!$D$2:$D$201,MATCH($B156,Products!$A$2:$A$201,0)),0)) | H156: =IF($B156="","",C156*G156*(1-D156)) | I156: =IF($B156="","",C156*IFERROR(INDEX(Products!$E$2:$E$201,MATCH($B156,Products!$A$2:$A$201,0)),0)) | J156: =IF($B156="","",H156-I156) | K156: =IF($A156="","",DATE(YEAR($A156),MONTH($A156),1))
E157: =IF($B157="","",IFERROR(INDEX(Products!$B$2:$B$201,MATCH($B157,Products!$A$2:$A$201,0)),"Unknown code")) | F157: =IF($B157="","",IFERROR(INDEX(Products!$C$2:$C$201,MATCH($B157,Products!$A$2:$A$201,0)),"")) | G157: =IF($B157="","",IFERROR(INDEX(Products!$D$2:$D$201,MATCH($B157,Products!$A$2:$A$201,0)),0)) | H157: =IF($B157="","",C157*G157*(1-D157)) | I157: =IF($B157="","",C157*IFERROR(INDEX(Products!$E$2:$E$201,MATCH($B157,Products!$A$2:$A$201,0)),0)) | J157: =IF($B157="","",H157-I157) | K157: =IF($A157="","",DATE(YEAR($A157),MONTH($A157),1))
E158: =IF($B158="","",IFERROR(INDEX(Products!$B$2:$B$201,MATCH($B158,Products!$A$2:$A$201,0)),"Unknown code")) | F158: =IF($B158="","",IFERROR(INDEX(Products!$C$2:$C$201,MATCH($B158,Products!$A$2:$A$201,0)),"")) | G158: =IF($B158="","",IFERROR(INDEX(Products!$D$2:$D$201,MATCH($B158,Products!$A$2:$A$201,0)),0)) | H158: =IF($B158="","",C158*G158*(1-D158)) | I158: =IF($B158="","",C158*IFERROR(INDEX(Products!$E$2:$E$201,MATCH($B158,Products!$A$2:$A$201,0)),0)) | J158: =IF($B158="","",H158-I158) | K158: =IF($A158="","",DATE(YEAR($A158),MONTH($A158),1))
E159: =IF($B159="","",IFERROR(INDEX(Products!$B$2:$B$201,MATCH($B159,Products!$A$2:$A$201,0)),"Unknown code")) | F159: =IF($B159="","",IFERROR(INDEX(Products!$C$2:$C$201,MATCH($B159,Products!$A$2:$A$201,0)),"")) | G159: =IF($B159="","",IFERROR(INDEX(Products!$D$2:$D$201,MATCH($B159,Products!$A$2:$A$201,0)),0)) | H159: =IF($B159="","",C159*G159*(1-D159)) | I159: =IF($B159="","",C159*IFERROR(INDEX(Products!$E$2:$E$201,MATCH($B159,Products!$A$2:$A$201,0)),0)) | J159: =IF($B159="","",H159-I159) | K159: =IF($A159="","",DATE(YEAR($A159),MONTH($A159),1))
... E1001: =IF($B1001="","",IFERROR(INDEX(Products!$B$2:$B$201,MATCH($B1001,Products!$A$2:$A$201,0)),"Unknown code")) | F1001: =IF($B1001="","",IFERROR(INDEX(Products!$C$2:$C$201,MATCH($B1001,Products!$A$2:$A$201,0)),"")) | G1001: =IF($B1001="","",IFERROR(INDEX(Products!$D$2:$D$201,MATCH($B1001,Products!$A$2:$A$201,0)),0)) | H1001: =IF($B1001="","",C1001*G1001*(1-D1001)) | I1001: =IF($B1001="","",C1001*IFERROR(INDEX(Products!$E$2:$E$201,MATCH($B1001,Products!$A$2:$A$201,0)),0)) | J1001: =IF($B1001="","",H1001-I1001) | K1001: =IF($A1001="","",DATE(YEAR($A1001),MONTH($A1001),1))
